shotstars/__init__.py
shotstars/shotstars.py
shotstars/stars.jpg
shotstars-4.11.dist-info/LICENSE
shotstars-4.11.dist-info/METADATA
shotstars-4.11.dist-info/WHEEL
shotstars-4.11.dist-info/entry_points.txt
shotstars-4.11.dist-info/top_level.txt
shotstars-4.11.dist-info/RECORD
