Metadata-Version: 2.1
Name: shotstars
Version: 4.11
Summary: A tool to track waning stars and detecting fake stars on Github
Author-email: Snooppr <snoopproject@protonmail.com>
Project-URL: Homepage, https://github.com/snooppr/shotstars
Project-URL: Donate, https://yoomoney.ru/to/4100111364257544
Keywords: termux,github,parser,stars,OSINT,scraping,secrets,scanner,analytics,fake stars
Classifier: Programming Language :: Python :: 3
Classifier: License :: OSI Approved :: GNU General Public License v3 (GPLv3)
Classifier: Operating System :: OS Independent
Classifier: Natural Language :: English
Classifier: Topic :: Internet :: WWW/HTTP :: Indexing/Search
Requires-Python: >=3.7
License-File: LICENSE
Requires-Dist: plotext ==5.3.2
Requires-Dist: plotly
Requires-Dist: rich >=13.0.1
Requires-Dist: requests
